[

    {
        "cid": 1,
        "content": "Some Text",
        "style": 1,
        "image": "upload/01.jpg",
        "rank": 1,
        "user": {
            "screen_name": "木炭星人",
            "avatar": "http://tp3.sinaimg.cn/1769414894/180/40043182605/0"
        }
    },
    {
        "cid": 2,
        "content": "Some Text",
        "style": 1,
        "image": "upload/01.jpg",
        "rank": 2,
        "user": {
            "screen_name": "木炭星人",
            "avatar": "http://tp3.sinaimg.cn/1769414894/180/40043182605/0"
        }
    },
    {
        "cid": 3,
        "content": "Some Text",
        "style": 1,
        "image": "upload/01.jpg",
        "rank": 3,
        "user": {
            "screen_name": "木炭星人",
            "avatar": "http://tp3.sinaimg.cn/1769414894/180/40043182605/0"
        }
    },
    {
        "cid": 4,
        "content": "Some Text",
        "style": 1,
        "image": "upload/01.jpg",
        "rank": 4,
        "user": {
            "screen_name": "木炭星人",
            "avatar": "http://tp3.sinaimg.cn/1769414894/180/40043182605/0"
        }
    },
    {
    "cid": 5,
    "content": "Some Text",
    "style": 1,
    "image": "upload/01.jpg",
    "rank": 5,
    "user": {
        "screen_name": "木炭星人",
        "avatar": "http://tp3.sinaimg.cn/1769414894/180/40043182605/0"
    }
}
]